zetaforge/Zetaforge.py
zetaforge/__init__.py
zetaforge/check_forge_dependencies.py
zetaforge/forge_cli.py
zetaforge/forge_runner.py
zetaforge/install_forge_dependencies.py
zetaforge/logger.py
zetaforge/mixpanel.py
zetaforge/mixpanel_client.py
zetaforge/rebind.py
zetaforge/block_maker/__init__.py
zetaforge/block_maker/__main__.py
zetaforge/block_maker/zetahelper.py
zetaforge/executables/README.md
zetaforge-0.4.3.dist-info/LICENSE
zetaforge-0.4.3.dist-info/METADATA
zetaforge-0.4.3.dist-info/WHEEL
zetaforge-0.4.3.dist-info/entry_points.txt
zetaforge-0.4.3.dist-info/top_level.txt
zetaforge-0.4.3.dist-info/RECORD
