Metadata-Version: 2.1
Name: zetaforge
Version: 0.4.3
Summary: zetaforge installer
Author-email: Zetane <info@zetane.com>
Requires-Python: >=3.10
License-File: LICENSE
Requires-Dist: setuptools==69.0.2
Requires-Dist: requests==2.31.0
Requires-Dist: boto3==1.34.79
Requires-Dist: mixpanel==4.10.1
Requires-Dist: langchain==0.1.15
Requires-Dist: langchain-openai==0.1.2
Requires-Dist: sentry-sdk===2.0.1
Requires-Dist: yaspin
Requires-Dist: rich
Requires-Dist: wheel>=0.45.1
